darmatch_pybind.cpython-37m-x86_64-linux-gnu.so
darmatch/__init__.py
darmatch/darmatch.py
darmatch-0.2.0.dist-info/LICENSE
darmatch-0.2.0.dist-info/METADATA
darmatch-0.2.0.dist-info/WHEEL
darmatch-0.2.0.dist-info/top_level.txt
darmatch-0.2.0.dist-info/RECORD
