Metadata-Version: 2.1
Name: darmatch
Version: 0.2.0
Summary: darmatch Python bindings
Home-page: https://github.com/zejunwang1/darmatch
Author: wangzejun
Author-email: wangzejunscut@126.com
License: MIT
Platform: UNKNOWN
Classifier: Development Status :: 3 - Alpha
Classifier: Intended Audience :: Developers
Classifier: Intended Audience :: Science/Research
Classifier: License :: OSI Approved :: MIT License
Classifier: Programming Language :: Python :: 2.7
Classifier: Programming Language :: Python :: 3.5
Classifier: Programming Language :: Python :: 3.6
Classifier: Programming Language :: Python :: 3.7
Classifier: Topic :: Software Development
Classifier: Topic :: Scientific/Engineering
Classifier: Operating System :: Microsoft :: Windows
Classifier: Operating System :: POSIX
Classifier: Operating System :: Unix
Classifier: Operating System :: MacOS
Requires-Dist: pybind11 (>=2.2)
Requires-Dist: setuptools (>=0.7.0)
Requires-Dist: typing
